rim/RIM.py
rim/__init__.py
rim/test.py
rim/test_specific_case.py
rim-0.3.16.dist-info/LICENSE
rim-0.3.16.dist-info/METADATA
rim-0.3.16.dist-info/WHEEL
rim-0.3.16.dist-info/top_level.txt
rim-0.3.16.dist-info/RECORD
