Metadata-Version: 2.1
Name: rim
Version: 0.3.16
Summary: A package for calculating RIM between three spatial objects
Home-page: https://github.com/SelfHealingMapsProject/RIM
Author: Ivan Majic
Author-email: imajicos@gmail.com
License: UNKNOWN
Platform: UNKNOWN
Classifier: Programming Language :: Python :: 3
Classifier: License :: OSI Approved :: MIT License
Classifier: Operating System :: OS Independent
Requires-Python: >=3.5
Requires-Dist: numpy (>=1.17.4)
Requires-Dist: Shapely (>=1.6.4)
